Metadata-Version: 1.0
Name: electron-insert-factors
Version: 1.0.0
Summary: Model electron insert factors.
Home-page: UNKNOWN
Author: Simon Biggs
Author-email: mail@simonbiggs.net
License: AGPL3+
Platform: UNKNOWN
